odoo/addons/web_widget_plotly_chart/README.rst
odoo/addons/web_widget_plotly_chart/__init__.py
odoo/addons/web_widget_plotly_chart/__manifest__.py
odoo/addons/web_widget_plotly_chart/i18n/ca.po
odoo/addons/web_widget_plotly_chart/i18n/da.po
odoo/addons/web_widget_plotly_chart/i18n/es.po
odoo/addons/web_widget_plotly_chart/i18n/it.po
odoo/addons/web_widget_plotly_chart/i18n/pt_BR.po
odoo/addons/web_widget_plotly_chart/i18n/web_widget_plotly_chart.pot
odoo/addons/web_widget_plotly_chart/readme/CONTRIBUTORS.md
odoo/addons/web_widget_plotly_chart/readme/CREDITS.md
odoo/addons/web_widget_plotly_chart/readme/DESCRIPTION.md
odoo/addons/web_widget_plotly_chart/readme/INSTALL.md
odoo/addons/web_widget_plotly_chart/readme/USAGE.md
odoo/addons/web_widget_plotly_chart/static/description/example.png
odoo/addons/web_widget_plotly_chart/static/description/icon.png
odoo/addons/web_widget_plotly_chart/static/description/index.html
odoo/addons/web_widget_plotly_chart/static/src/js/widget_plotly.esm.js
odoo/addons/web_widget_plotly_chart/static/src/js/widget_plotly.xml
odoo/addons/web_widget_plotly_chart/static/src/lib/plotly/plotly-2.32.0.min.js
odoo_addon_web_widget_plotly_chart-17.0.1.0.0.2.dist-info/METADATA
odoo_addon_web_widget_plotly_chart-17.0.1.0.0.2.dist-info/WHEEL
odoo_addon_web_widget_plotly_chart-17.0.1.0.0.2.dist-info/top_level.txt
odoo_addon_web_widget_plotly_chart-17.0.1.0.0.2.dist-info/RECORD
