Metadata-Version: 2.1
Name: odoo-addon-web_widget_plotly_chart
Version: 17.0.1.0.0.2
Requires-Python: >=3.10
Requires-Dist: odoo>=17.0a,<17.1dev
Requires-Dist: plotly==5.22.0
Summary: Allow to draw plotly charts.
Home-page: https://github.com/OCA/web
License: LGPL-3
Author: LevelPrime srl, Odoo Community Association (OCA)
Author-email: support@odoo-community.org
Classifier: Programming Language :: Python
Classifier: Framework :: Odoo
Classifier: Framework :: Odoo :: 17.0
Classifier: License :: OSI Approved :: GNU Lesser General Public License v3 (LGPLv3)
